hokage/__init__.py
hokage/database.py
hokage/iam.py
hokage/s3.py
hokage/secrets_manager.py
hokage/ses.py
hokage/slack.py
hokage/sqs.py
hokage/webhook.py
hokage/zendesk.py
hokage/utils/__init__.py
hokage/utils/email_validator.py
hokage/utils/ssh_validator.py
tests/__init__.py
tests/hokage_test.py
hokage-0.0.14.dist-info/LICENSE
hokage-0.0.14.dist-info/METADATA
hokage-0.0.14.dist-info/WHEEL
hokage-0.0.14.dist-info/top_level.txt
hokage-0.0.14.dist-info/RECORD
